{
	"class" : {
		"isAbstract" : "jr 1/26/2017 17:27" },
	"instance" : {
		"addPackage" : "jr 1/26/2020 23:53",
		"assertVersion:containsMethod:" : "jr 7/21/2017 02:59",
		"changeLogSuppressor" : "jr 4/29/2018 16:50",
		"classFactory" : "jr 10/1/2017 01:44",
		"denyChangesInWorkingCopy" : "jr 10/12/2020 22:48",
		"newRepository" : "jr 1/26/2017 17:15",
		"newStore" : "jr 1/29/2017 22:20",
		"newWorkingCopy" : "jr 1/26/2017 17:05",
		"performTest" : "jr 9/22/2020 00:41",
		"repositoryRootDirectory" : "jr 10/31/2017 23:46",
		"setUp" : "jr 10/31/2017 23:46",
		"targetClass" : "jr 1/26/2017 17:21",
		"tearDown" : "jr 9/20/2019 20:30",
		"testAddMultipleObjectsSuccessively" : "jr 10/19/2020 20:51",
		"testAdditionNotLoaded" : "jr 10/4/2020 22:06",
		"testCherryPickDoesNotSaveUnrelatedChanges" : "jr 10/24/2020 17:28",
		"testCherryPickOfOrphanedVersion" : "jr 10/11/2020 23:07",
		"testCherryPickWithConflicts" : "jr 4/12/2020 10:23",
		"testCherryPickWithConflictsChooseRemote" : "jr 4/12/2020 10:23",
		"testCherryPickWithoutConflicts" : "jr 4/12/2020 10:23",
		"testDiffWithParent" : "jr 3/2/2020 22:55",
		"testDiscardUnsavedChangeToUnloadedArtifact" : "jr 10/12/2020 22:48",
		"testMergeFastForward" : "jr 9/22/2020 22:19",
		"testMergeRemovalAndChange" : "jr 9/22/2020 00:18",
		"testMergeSingleArtifact" : "jr 3/2/2020 23:35",
		"testMergeTwoOrphanedVersions" : "jr 10/12/2020 21:57",
		"testMergeVersionWithLoadedObjects" : "jr 3/2/2020 23:35",
		"testMergeWithAddedArtifactOnBothSides" : "jr 9/22/2020 00:25",
		"testMergeWithConflicts" : "jr 9/22/2020 00:33",
		"testMergeWithConflictsChooseRemote" : "jr 9/22/2020 00:35",
		"testMergeWithRemovedArtifactOnBothSides" : "jr 9/22/2020 00:29",
		"testMergeWithoutConflicts" : "jr 9/22/2020 00:11",
		"testOldMergeRemovalAndChange" : "jr 9/22/2020 00:16",
		"testOldMergeTwoOrphanedVersions" : "jr 10/12/2020 21:58",
		"testOldMergeWithAddedArtifactOnBothSides" : "jr 9/22/2020 00:23",
		"testOldMergeWithConflicts" : "jr 9/22/2020 00:26",
		"testOldMergeWithConflictsChooseRemote" : "jr 9/22/2020 00:34",
		"testOldMergeWithRemovedArtifactOnBothSides" : "jr 9/22/2020 00:28",
		"testOldMergeWithoutConflicts" : "jr 9/22/2020 00:14",
		"testPatchUnloadedArtifact" : "jr 10/4/2020 23:57",
		"testReaddedObjectAfterMergeInIncomingLoadOrderPosition" : "jr 10/24/2020 18:10",
		"testReaddedObjectAfterMergeInSameLoadOrderPosition" : "jr 10/24/2020 18:13",
		"testRemovePackage" : "jr 1/26/2020 23:54",
		"testRemovedUnsavedArtifactStaysRemoved" : "jr 10/19/2020 20:45",
		"testRestoreClass" : "jr 8/11/2020 23:40",
		"testRestorePackage" : "jr 3/2/2020 23:24",
		"testSaveTimestampIsNow" : "jr 8/25/2020 19:13",
		"testSwitchAndMoveOverToBranchAtSameVersion" : "jr 3/2/2020 23:23",
		"testSwitchBranch" : "jr 3/2/2020 23:23",
		"testSwitchBranchAndMoveOverUnsavedChanges" : "jr 3/2/2020 23:37",
		"testSwitchBranchAndMoveOverUnsavedChangesInAddedArtifact" : "jr 3/2/2020 23:37",
		"testSwitchBranchAndMoveOverUnsavedChangesWithConflict" : "jr 3/2/2020 23:37",
		"testSwitchToBranchAtSameVersion" : "jr 3/2/2020 23:38",
		"testTrackingAClass" : "jr 10/12/2020 22:49",
		"testTrackingAPackage" : "jr 10/12/2020 22:49",
		"testTrackingObject" : "jr 10/12/2020 22:49",
		"testTrackingText" : "jr 3/3/2020 00:15",
		"testTrackingWorkspaceMorph" : "jr 3/3/2020 00:16",
		"workingCopy" : "jr 9/21/2017 20:58" } }
