{
	"class" : {
		"entangle:" : "jr 4/11/2021 19:36" },
	"instance" : {
		"asMaterializedReference" : "jr 4/11/2021 20:08",
		"installTarget" : "jr 4/11/2021 21:03",
		"isPopulated" : "jr 4/11/2021 19:28",
		"newNameFragment" : "jr 4/11/2021 19:24",
		"populate:in:reflectedIn:with:" : "jr 4/11/2021 20:10",
		"populatedTarget" : "jr 4/11/2021 20:11",
		"reflect:in:" : "jr 4/11/2021 19:25",
		"reflect:in:put:" : "jr 4/11/2021 20:03",
		"setActualReference:" : "jr 4/11/2021 19:35",
		"setEntangledReferences:" : "jr 4/11/2021 19:36" } }
