{
	"class" : {
		"aiffEncoding" : "mad 9/20/2023 17:58",
		"assetTypeName" : "mad 9/20/2023 19:11",
		"defaultEncoding" : "mad 9/20/2023 18:43",
		"encodingName:" : "mad 9/20/2023 19:03",
		"validEncodings" : "mad 9/20/2023 17:58",
		"wavEncoding" : "mad 9/20/2023 17:58" },
	"instance" : {
		"canReadVersionFrom:" : "mad 10/19/2023 12:56",
		"doPostUpdateMigrationsIn:" : "mad 1/12/2024 12:34",
		"fixNilEncoding" : "mad 1/12/2024 12:37",
		"isValidVersion:" : "mad 10/21/2023 21:33",
		"readVersionFrom:" : "mad 10/17/2023 12:22",
		"transformVersion:ifFail:" : "mad 10/17/2023 12:33",
		"versionAsMorph:" : "mad 9/21/2023 12:37",
		"versionTypeName" : "mad 10/21/2023 22:28",
		"writeVersion:on:" : "mad 9/20/2023 17:57" } }
