{
	"class" : {
		 },
	"instance" : {
		"definitionAsString:" : "mad 9/10/2023 16:12",
		"exclude" : "mad 9/7/2023 16:38",
		"fsPath" : "mad 9/6/2023 19:12",
		"hasConflict" : "mad 9/9/2023 18:25",
		"include" : "mad 9/7/2023 16:38",
		"initialize" : "mad 9/7/2023 16:36",
		"isExcluded" : "mad 9/7/2023 16:36",
		"isExcluded:" : "mad 9/11/2023 14:39",
		"operation" : "mad 9/10/2023 14:31",
		"package" : "mad 9/6/2023 19:20",
		"path" : "mad 9/10/2023 18:51",
		"someDefinition" : "mad 9/10/2023 18:51" } }
