{
	"class" : {
		"withMapper:old:potentiallyRemoved:changeSets:" : "mad 2/20/2024 15:04" },
	"instance" : {
		"allMappers" : "mad 3/19/2024 21:25",
		"canMapperBeRemovedAfterMaterializeIn:" : "mad 7/3/2024 16:27",
		"canMapperBeRemovedAfterSerializeInto:" : "mad 7/3/2024 16:27",
		"canMapperBeRemovedAtAll" : "mad 7/3/2024 16:27",
		"changes" : "mad 9/20/2023 12:04",
		"mapperChangeSets" : "mad 2/20/2024 14:51",
		"mapperChangeSets:" : "mad 2/20/2024 14:51",
		"materializeIn:" : "mad 2/20/2024 15:50",
		"newMappers" : "mad 2/20/2024 15:30",
		"newMappersAfterMaterializeIn:" : "mad 2/20/2024 15:32",
		"newMappersAfterSerializeInto:" : "mad 2/20/2024 15:31",
		"newMappersWithRemovalCheck:" : "mad 2/20/2024 15:30",
		"oldMappers" : "mad 9/20/2023 12:00",
		"oldMappers:" : "mad 9/20/2023 12:00",
		"potentiallyRemovedMappers" : "mad 2/20/2024 15:00",
		"potentiallyRemovedMappers:" : "mad 2/20/2024 15:00",
		"referenceIn:" : "mad 9/20/2023 12:02",
		"serializeInto:" : "mad 2/20/2024 15:31" } }
